<?xml version="1.0" encoding="utf-8"?>
<mosinstall type="module" version="1.0.0">
	<name>Персональный модуль</name>
	<author>Joostina! Project</author>
	<creationDate>Октябрь 2008</creationDate>
	<copyright>(C) 2008-2010 Joostina team.</copyright>
	<license>http://www.gnu.org/licenses/gpl-2.0.htm GNU/GPL</license>
	<authorEmail>joostinacms@gmail.com</authorEmail>
	<authorUrl>www.joostina.ru</authorUrl>
	<version>1.0.0</version>
	<description>Персональный модуль</description>
	<params>
		<param name="moduleclass_sfx" type="text" default="" label="CSS-суффикс класса модуля" description="Суффикс, который будет использован в описании класса (table.moduletable) таблицы стилей (CSS) модуля. Это позволяет использовать индивидуальный стиль модуля." />
		<param name="cache" type="radio" default="0" label="Кэширование модуля" description="Выберите, кэшировать ли содержимое этого модуля">
			<option value="1">Да</option>
			<option value="0">Нет</option>
		</param>
		<param name="@spacer" type="spacer" default="" label="" description="" />
		<param name="rssurl" type="text" size="50" default="" label="URL-адрес RSS" description="Введите URL-адрес ленты RSS/RDF" />
		<param name="rsstitle" type="radio" default="1" label="Заголовок ленты" description="Отображаемый заголовок ленты новостей">
			<option value="1">Да</option>
			<option value="0">Нет</option>
		</param>
		<param name="rssdesc" type="radio" default="1" label="Описание ленты" description="Показывает текст описания для всей ленты">
			<option value="1">Да</option>
			<option value="0">Нет</option>
		</param>
		<param name="rssimage" type="radio" default="1" label="Изображение ленты" description="Показывает изображение, ассоциированное со всей лентой">
			<option value="1">Да</option>
			<option value="0">Нет</option>
		</param>
		<param name="rssitems" type="text" default="3" label="Объектов" description="Введите количество отображаемых объектов RSS" />
		<param name="rssitemdesc" type="radio" default="1" label="Описание объекта" description="Показывает описание или вводный текст отдельных объектов новостей">
			<option value="1">Да</option>
			<option value="0">Нет</option>
		</param>
		<param name="word_count" type="text" size="6" default="0" label="Подсчет слов" description="Позволяет Вам ограничить количество текста описания видимого объекта. При 0 показывается весь текст" />
		<param name="rsscache" type="text" size="6" default="3600" label="Время жизни кэша RSS" description="Установите время кэширования для этой ленты RSS" />
	</params>
</mosinstall>